examples/__init__.py
examples/nameko/__init__.py
examples/nameko/services.py
ipecac/__init__.py
ipecac/cli.py
ipecac/settings.py
ipecac/tools/__init__.py
ipecac/tools/extract.py
ipecac/tools/generate.py
ipecac/tools/scan.py
tasks/__init__.py
tasks/build.py
tasks/lint.py
tasks/test.py
test/__init__.py
test/test_extract.py
test/test_generate.py
test/test_scan.py
test/utils.py
ipecac-0.2.dist-info/METADATA
ipecac-0.2.dist-info/WHEEL
ipecac-0.2.dist-info/entry_points.txt
ipecac-0.2.dist-info/top_level.txt
ipecac-0.2.dist-info/RECORD
